pydynamicestimator/__init__.py
pydynamicestimator/__main__.py
pydynamicestimator/config.py
pydynamicestimator/configs/config_ideal.py
pydynamicestimator/configs/config_standard.py
pydynamicestimator/devices/__init__.py
pydynamicestimator/devices/device.py
pydynamicestimator/devices/inverter.py
pydynamicestimator/devices/static.py
pydynamicestimator/devices/synchronous.py
pydynamicestimator/main.py
pydynamicestimator/measurements/__init__.py
pydynamicestimator/measurements/measurements.py
pydynamicestimator/run.py
pydynamicestimator/system.py
pydynamicestimator/testcases/IEEE39_bus/est_dist.txt
pydynamicestimator/testcases/IEEE39_bus/est_param.txt
pydynamicestimator/testcases/IEEE39_bus/sim_dist.txt
pydynamicestimator/testcases/IEEE39_bus/sim_param.txt
pydynamicestimator/testcases/IEEE39_bus_ideal/est_dist.txt
pydynamicestimator/testcases/IEEE39_bus_ideal/est_param.txt
pydynamicestimator/testcases/IEEE39_bus_ideal/sim_dist.txt
pydynamicestimator/testcases/IEEE39_bus_ideal/sim_param.txt
pydynamicestimator/testcases/IEEE39_bus_inverter/est_dist.txt
pydynamicestimator/testcases/IEEE39_bus_inverter/est_param.txt
pydynamicestimator/testcases/IEEE39_bus_inverter/sim_dist.txt
pydynamicestimator/testcases/IEEE39_bus_inverter/sim_param.txt
pydynamicestimator/tests/__init__.py
pydynamicestimator/tests/baselines/baseline_result_est.pkl
pydynamicestimator/tests/baselines/baseline_result_sim.pkl
pydynamicestimator/tests/baselines/create_baseline.py
pydynamicestimator/tests/test_recur_est.py
pydynamicestimator/tests/test_recur_sim.py
pydynamicestimator/tests/test_run_ideal.py
pydynamicestimator/utils/data_loader.py
pydynamicestimator/utils/generate_metadata.py
pydynamicestimator/utils/update_last_modified.sh
pydynamicestimator-0.4.7.dist-info/entry_points.txt
pydynamicestimator-0.4.7.dist-info/LICENSE.txt
pydynamicestimator-0.4.7.dist-info/METADATA
pydynamicestimator-0.4.7.dist-info/WHEEL
pydynamicestimator-0.4.7.dist-info/RECORD
