Metadata-Version: 2.1
Name: pydynamicestimator
Version: 0.4.7
Summary: A dynamic estimator for power systems
Home-page: https://gitlab.nccr-automation.ch/mkatanic/powerdynamicestimator
License: GPL-3.0-or-later
Author: Milos Katanic
Author-email: mkatanic@ethz.ch
Requires-Python: >=3.10,<4.0
Classifier: License :: OSI Approved :: GNU General Public License v3 or later (GPLv3+)
Classifier: Programming Language :: Python :: 3
Classifier: Programming Language :: Python :: 3.10
Classifier: Programming Language :: Python :: 3.11
Classifier: Programming Language :: Python :: 3.12
Requires-Dist: casadi (>=3.6.5,<4.0.0)
Requires-Dist: matplotlib (>=3.8.3,<4.0.0)
Requires-Dist: nbsphinx (>=0.9.7,<0.10.0)
Requires-Dist: numpy (>=2.2.4,<3.0.0)
Requires-Dist: pandas (>=2.2.3,<3.0.0)
Requires-Dist: pydantic (>=2.10.3,<3.0.0)
Requires-Dist: scipy (>=1.12.0,<2.0.0)
Requires-Dist: sphinx (>=8.1.3,<9.0.0)
Requires-Dist: tabulate (>=0.9.0,<0.10.0)
Project-URL: Repository, https://gitlab.nccr-automation.ch/mkatanic/powerdynamicestimator
